odoo/addons/sale_amount_payment_link/README.rst
odoo/addons/sale_amount_payment_link/__init__.py
odoo/addons/sale_amount_payment_link/__manifest__.py
odoo/addons/sale_amount_payment_link/i18n/sale_amount_payment_link.pot
odoo/addons/sale_amount_payment_link/readme/CONTRIBUTORS.rst
odoo/addons/sale_amount_payment_link/readme/DESCRIPTION.rst
odoo/addons/sale_amount_payment_link/readme/USAGE.rst
odoo/addons/sale_amount_payment_link/static/description/icon.png
odoo/addons/sale_amount_payment_link/static/description/index.html
odoo/addons/sale_amount_payment_link/tests/__init__.py
odoo/addons/sale_amount_payment_link/tests/test_sale_amount_payment_link.py
odoo/addons/sale_amount_payment_link/wizards/__init__.py
odoo/addons/sale_amount_payment_link/wizards/sale_amount_payment_link.py
odoo14_addon_sale_amount_payment_link-14.0.1.0.1.dist-info/METADATA
odoo14_addon_sale_amount_payment_link-14.0.1.0.1.dist-info/WHEEL
odoo14_addon_sale_amount_payment_link-14.0.1.0.1.dist-info/top_level.txt
odoo14_addon_sale_amount_payment_link-14.0.1.0.1.dist-info/RECORD
